Toast4Windows/__init__.py
Toast4Windows/toast4windows.py
Toast4Windows-0.0.5.dist-info/LICENSE
Toast4Windows-0.0.5.dist-info/METADATA
Toast4Windows-0.0.5.dist-info/WHEEL
Toast4Windows-0.0.5.dist-info/top_level.txt
Toast4Windows-0.0.5.dist-info/RECORD
