Metadata-Version: 2.1
Name: Toast4Windows
Version: 0.0.5
Summary: Python library based on C++ to show Windows 10 based toast notification. 
Home-page: UNKNOWN
Author: Pankaj Pande
Author-email: pkjpande@gmail.com
License: UNKNOWN
Keywords: python,windows toast,toast,notifications,windows notifications,windows popup
Platform: UNKNOWN
Classifier: Development Status :: 1 - Planning
Classifier: Intended Audience :: Developers
Classifier: Programming Language :: Python :: 3
Classifier: Operating System :: Unix
Classifier: Operating System :: MacOS :: MacOS X
Classifier: Operating System :: Microsoft :: Windows
Requires-Dist: winrt
